gibberish_detector/__init__.py
gibberish_detector/__main__.py
gibberish_detector/__version__.py
gibberish_detector/detector.py
gibberish_detector/exceptions.py
gibberish_detector/main.py
gibberish_detector/model.py
gibberish_detector/serializer.py
gibberish_detector/trainer.py
gibberish_detector/util.py
gibberish_detector/usage/__init__.py
gibberish_detector/usage/common.py
gibberish_detector/usage/detect.py
gibberish_detector/usage/train.py
gibberish_detector-0.1.1.dist-info/LICENSE
gibberish_detector-0.1.1.dist-info/METADATA
gibberish_detector-0.1.1.dist-info/WHEEL
gibberish_detector-0.1.1.dist-info/entry_points.txt
gibberish_detector-0.1.1.dist-info/top_level.txt
gibberish_detector-0.1.1.dist-info/RECORD
