Metadata-Version: 2.1
Name: gibberish-detector
Version: 0.1.1
Summary: Detects gibberish strings.
Home-page: https://github.com/domanchi/gibberish-detector
Author: Aaron Loo <admin@aaronloo.com>
License: MIT
Platform: UNKNOWN
Classifier: Development Status :: 4 - Beta
Classifier: Environment :: Console
Classifier: Intended Audience :: Developers
Classifier: License :: OSI Approved :: MIT License
Classifier: Programming Language :: Python :: 3 :: Only
Classifier: Topic :: Software Development :: Libraries :: Python Modules
Classifier: Topic :: Text Processing :: General
Classifier: Topic :: Utilities
